vulture/__init__.py
vulture/__main__.py
vulture/config.py
vulture/core.py
vulture/lines.py
vulture/noqa.py
vulture/utils.py
vulture/version.py
vulture/whitelists/argparse_whitelist.py
vulture/whitelists/ast_whitelist.py
vulture/whitelists/collections_whitelist.py
vulture/whitelists/ctypes_whitelist.py
vulture/whitelists/enum_whitelist.py
vulture/whitelists/logging_whitelist.py
vulture/whitelists/pint_whitelist.py
vulture/whitelists/socketserver_whitelist.py
vulture/whitelists/string_whitelist.py
vulture/whitelists/sys_whitelist.py
vulture/whitelists/threading_whitelist.py
vulture/whitelists/unittest_whitelist.py
vulture/whitelists/whitelist_utils.py
vulture-2.13.dist-info/LICENSE.txt
vulture-2.13.dist-info/METADATA
vulture-2.13.dist-info/WHEEL
vulture-2.13.dist-info/entry_points.txt
vulture-2.13.dist-info/top_level.txt
vulture-2.13.dist-info/RECORD
