Metadata-Version: 2.1
Name: vulture
Version: 2.13
Summary: Find dead code
Home-page: https://github.com/jendrikseipp/vulture
Author: Jendrik Seipp
Author-email: jendrikseipp@gmail.com
License: MIT
Keywords: dead-code-removal
Classifier: Development Status :: 5 - Production/Stable
Classifier: Environment :: Console
Classifier: Intended Audience :: Developers
Classifier: License :: OSI Approved :: MIT License
Classifier: Programming Language :: Python
Classifier: Programming Language :: Python :: 3
Classifier: Programming Language :: Python :: 3.8
Classifier: Programming Language :: Python :: 3.9
Classifier: Programming Language :: Python :: 3.10
Classifier: Programming Language :: Python :: 3.11
Classifier: Programming Language :: Python :: 3.12
Classifier: Programming Language :: Python :: 3.13
Classifier: Programming Language :: Python :: Implementation :: CPython
Classifier: Programming Language :: Python :: Implementation :: PyPy
Classifier: Topic :: Software Development :: Quality Assurance
Requires-Python: >=3.8
License-File: LICENSE.txt
